jtex/DefBuilder.py
jtex/DocModel.py
jtex/LatexBuilder.py
jtex/PublicTemplateLoader.py
jtex/TemplateLoader.py
jtex/TemplateOptions.py
jtex/TemplateRenderer.py
jtex/TexFormat.py
jtex/__init__.py
jtex/__main__.py
jtex/utils.py
jtex/version.py
jtex/builtin_template/curvenote.png
jtex/builtin_template/template.tex
jtex/builtin_template/template.yml
jtex/cli/__init__.py
jtex/cli/app.py
jtex/cli/freeform.py
jtex/cli/render.py
jtex/cli/validate.py
jtex/defs/cmd-bibstyle-abbrvnat.def
jtex/defs/cmd-citestyle-authoryear-rounded.def
jtex/defs/cmd-raggedbottom.def
jtex/defs/cmd-shortdate.def
jtex/defs/cmd-sloppy.def
jtex/defs/package-base.def
jtex/defs/package-fancyvrb.def
jtex/defs/package-mdframed.def
jtex/defs/package-minted.def
jtex/defs/package-natbib.def
jtex/defs/package-xcolor.def
jtex/defs/passopts-base.def
jtex/defs/passopts-code-xcolor.def
jtex/defs/passopts-mdframed.def
jtex/defs/setup-aside-callout.def
jtex/defs/setup-aside-framed.def
jtex/defs/setup-aside-marginpar.def
jtex/defs/setup-aside-mdframed.def
jtex/defs/setup-base.def
jtex/defs/setup-bib-style.def
jtex/defs/setup-callout-framed.def
jtex/defs/setup-callout-mdframed.def
jtex/defs/setup-callout.def
jtex/defs/setup-cite-style.def
jtex/defs/setup-code-framed.def
jtex/defs/setup-code-minted.def
jtex/defs/setup-code-verbatim.def
jtex/defs/setup-hyperref-hidelinks.def
jtex/options/AsideSchemaOption.py
jtex/options/BibstyleSchemaOption.py
jtex/options/BooleanSchemaOption.py
jtex/options/CalloutSchemaOption.py
jtex/options/CitestyleSchemaOption.py
jtex/options/CodeSchemaOption.py
jtex/options/HideLinksSchemaOption.py
jtex/options/NatbibSchemaOption.py
jtex/options/RaggedBottomOption.py
jtex/options/SchemaOption.py
jtex/options/SchemaOptionDefs.py
jtex/options/SloppySchemaOption.py
jtex/options/StringSchemaOption.py
jtex/options/__init__.py
jtex/schema/config.schema.yml
jtex/schema/frontmatter.schema.yml
jtex/schema/template.schema.yml
jtex-0.3.15.dist-info/LICENSE
jtex-0.3.15.dist-info/METADATA
jtex-0.3.15.dist-info/WHEEL
jtex-0.3.15.dist-info/entry_points.txt
jtex-0.3.15.dist-info/top_level.txt
jtex-0.3.15.dist-info/RECORD
